cinderlib/__init__.py
cinderlib/_fake_packages.py
cinderlib/cinderlib.py
cinderlib/exception.py
cinderlib/objects.py
cinderlib/serialization.py
cinderlib/utils.py
cinderlib/bin/venv-privsep-helper
cinderlib/cmd/__init__.py
cinderlib/cmd/cinder_cfg_to_python.py
cinderlib/cmd/cinder_to_yaml.py
cinderlib/persistence/__init__.py
cinderlib/persistence/base.py
cinderlib/persistence/dbms.py
cinderlib/persistence/memory.py
cinderlib/tests/__init__.py
cinderlib/tests/functional/__init__.py
cinderlib/tests/functional/base_tests.py
cinderlib/tests/functional/ceph.yaml
cinderlib/tests/functional/lvm.yaml
cinderlib/tests/functional/test_basic.py
cinderlib/tests/unit/__init__.py
cinderlib/tests/unit/base.py
cinderlib/tests/unit/test_cinderlib.py
cinderlib/tests/unit/test_serialization.py
cinderlib/tests/unit/utils.py
cinderlib/tests/unit/objects/__init__.py
cinderlib/tests/unit/objects/test_connection.py
cinderlib/tests/unit/objects/test_snapshot.py
cinderlib/tests/unit/objects/test_volume.py
cinderlib/tests/unit/persistence/__init__.py
cinderlib/tests/unit/persistence/base.py
cinderlib/tests/unit/persistence/helper.py
cinderlib/tests/unit/persistence/test_base.py
cinderlib/tests/unit/persistence/test_dbms.py
cinderlib/tests/unit/persistence/test_memory.py
cinderlib-5.2.0.dist-info/AUTHORS
cinderlib-5.2.0.dist-info/LICENSE
cinderlib-5.2.0.dist-info/METADATA
cinderlib-5.2.0.dist-info/WHEEL
cinderlib-5.2.0.dist-info/entry_points.txt
cinderlib-5.2.0.dist-info/pbr.json
cinderlib-5.2.0.dist-info/top_level.txt
cinderlib-5.2.0.dist-info/RECORD
