Metadata-Version: 2.1
Name: cinderlib
Version: 5.2.0
Summary: Direct usage of Cinder Block Storage drivers without the services
Home-page: https://docs.openstack.org/cinderlib/latest/
Author: OpenStack
Author-email: openstack-discuss@lists.openstack.org
License: UNKNOWN
Platform: UNKNOWN
Classifier: Environment :: OpenStack
Classifier: Intended Audience :: Information Technology
Classifier: Intended Audience :: System Administrators
Classifier: Intended Audience :: Developers
Classifier: License :: OSI Approved :: Apache Software License
Classifier: Operating System :: POSIX :: Linux
Classifier: Programming Language :: Python
Classifier: Programming Language :: Python :: Implementation :: CPython
Classifier: Programming Language :: Python :: 3 :: Only
Classifier: Programming Language :: Python :: 3
Classifier: Programming Language :: Python :: 3.8
Classifier: Programming Language :: Python :: 3.9
Classifier: Programming Language :: Python :: 3.10
Requires-Python: >=3.8
Requires-Dist: cinder (<24.0.0,>=23.0.0)
Requires-Dist: importlib-metadata (>=1.7.0)
Requires-Dist: os-brick (>=6.4.0)
Requires-Dist: importlib-resources (>=3.2.1) ; (python_version<'3.10')
